PySegmentKit/__init__.py
PySegmentKit/main.py
PySegmentKit/bin/linux/julius
PySegmentKit/bin/macos/julius
PySegmentKit/bin/windows/julius.exe
PySegmentKit/models/hmmdefs_monof_mix16_gid.binhmm
PySegmentKit/models/hmmdefs_ptm_gid.binhmm
PySegmentKit/models/logicalTri
PySegmentKit/wav/sample.txt
PySegmentKit/wav/sample.wav
PySegmentKit-0.2.1.dist-info/LICENSE
PySegmentKit-0.2.1.dist-info/METADATA
PySegmentKit-0.2.1.dist-info/WHEEL
PySegmentKit-0.2.1.dist-info/top_level.txt
PySegmentKit-0.2.1.dist-info/RECORD
