Metadata-Version: 2.1
Name: PySegmentKit
Version: 0.2.1
Summary: A python-port of julius-speech/segmentation-kit
Home-page: https://github.com/urushiyama/PySegmentKit
Author: Yuta Urushiyama
Author-email: aswif10flis1ntkb@gmail.com
License: MIT
Platform: UNKNOWN
Classifier: Programming Language :: Python :: 3
Classifier: License :: OSI Approved :: MIT License
Classifier: Operating System :: OS Independent
Requires-Python: >=3.6
